{
	"name": "My theme",
	"slug": "my-theme",
	"version": "1.0.0",
	"version_date": "2025-01-11 00:00:00",
	"theme_uri": "https://github.com/studiochampgauche/wordpress-theme-test",
	"package": "https://github.com/studiochampgauche/wordpress-theme-test/archive/refs/heads/master.zip",
	"author": "",
	"author_uri": "",
	"requires_wp": "6.1",
	"requires_php": "8.2",
	"tested": "6.7.1",
	"license": "",
	"license_uri": "",
	"downloads": {
		"active": 3,
		"total": 4
	},
	"tags": [],
	"description": ""
}